fpzip.cpython-310-darwin.so
rms_fpzip-1.3.5.dist-info/RECORD
rms_fpzip-1.3.5.dist-info/LICENSE
rms_fpzip-1.3.5.dist-info/AUTHORS
rms_fpzip-1.3.5.dist-info/WHEEL
rms_fpzip-1.3.5.dist-info/top_level.txt
rms_fpzip-1.3.5.dist-info/METADATA
