Metadata-Version: 2.1
Name: rms-fpzip
Version: 1.3.5
Summary: Numpy wrapper for fpzip algorithm (P. Lindstrom & M. Isenburg, 2006) RMS Fork
Home-page: https://github.com/SETI/rms-fpzip/
Author: William Silversmith
Author-email: ws9@princeton.edu
Maintainer: Robert French
Maintainer-email: rfrench@seti.org
License: BSD
Project-URL: homepage, https://github.com/SETI/rms-fpzip
Project-URL: Repository, https://github.com/SETI/rms-fpzip
Project-URL: Source, https://github.com/SETI/rms-fpzip
Project-URL: Issues, https://github.com/SETI/rms-fpzip/issues
Classifier: Development Status :: 5 - Production/Stable
Classifier: Natural Language :: English
Classifier: Intended Audience :: Developers
Classifier: Topic :: Scientific/Engineering
Classifier: Topic :: System :: Archiving :: Compression
Classifier: License :: OSI Approved :: Apache Software License
Classifier: Programming Language :: Python :: 3.9
Classifier: Programming Language :: Python :: 3.10
Classifier: Programming Language :: Python :: 3.11
Classifier: Programming Language :: Python :: 3.12
Classifier: Programming Language :: Python :: 3.13
Classifier: Operating System :: MacOS :: MacOS X
Classifier: Operating System :: POSIX :: Linux
Classifier: Operating System :: Microsoft :: Windows
Requires-Python: >=3.9
License-File: LICENSE
License-File: AUTHORS
Requires-Dist: numpy
